tweets_preprocess/__init__.py
tweets_preprocess/preprocess.py
tweets_preprocess-0.2.4.dist-info/METADATA
tweets_preprocess-0.2.4.dist-info/WHEEL
tweets_preprocess-0.2.4.dist-info/top_level.txt
tweets_preprocess-0.2.4.dist-info/RECORD
