Metadata-Version: 2.1
Name: tweets-preprocess
Version: 0.2.4
Summary: Library for tweets preprocessing
Home-page: https://tweets_preprocess.readthedocs.io/
Author: Anusha Kotha
Author-email: anusha.kotha@indianpac.com
License: MIT
Classifier: Intended Audience :: Developers
Classifier: License :: OSI Approved :: MIT License
Classifier: Programming Language :: Python
Classifier: Programming Language :: Python :: 3.9
Classifier: Operating System :: OS Independent
Requires-Dist: numpy
Requires-Dist: pandas
Requires-Dist: regex
